eals/__init__.py
eals/eals.py
eals/serializer.py
eals/util.py
eals_py312-0.9.7.dist-info/WHEEL
eals_py312-0.9.7.dist-info/METADATA
eals_py312-0.9.7.dist-info/RECORD
