Metadata-Version: 2.3
Name: eals-py312
Version: 0.9.7
Summary: eALS - Element-wise Alternating Least Squares
Author: Akira Kitauchi, Michihiro Nakamura
Author-email: Akira Kitauchi <kitauchi@gmail.com>, Michihiro Nakamura <nakamichi@nakamichi.org>
Requires-Dist: scipy>=1.10.1
Requires-Dist: numba>=0.59.0
Requires-Dist: joblib>=1.2.0
Maintainer: Artamonov Daniel
Maintainer-email: Artamonov Daniel <christerbin@gmail.com>
Requires-Python: >=3.12
Project-URL: homepage, https://github.com/newspicks
Project-URL: repository, https://github.com/newspicks/eals
